kamal/__init__.py
kamal/outils.py
Kamalshkeir-1.0.dist-info/METADATA
Kamalshkeir-1.0.dist-info/WHEEL
Kamalshkeir-1.0.dist-info/top_level.txt
Kamalshkeir-1.0.dist-info/RECORD
