Metadata-Version: 2.1
Name: Kamalshkeir
Version: 1.0
Summary: UNKNOWN
Home-page: UNKNOWN
Author: Kamal Shkeir
Author-email: kamalshkeir@yahoo.fr
License: UNKNOWN
Platform: UNKNOWN
Requires-Dist: six
Requires-Dist: cryptography
Requires-Dist: pyotp
Requires-Dist: qrcode
Requires-Dist: twilio
